LICENSE
MANIFEST.in
README.rst
setup.py
django_profiler.egg-info/PKG-INFO
django_profiler.egg-info/SOURCES.txt
django_profiler.egg-info/dependency_links.txt
django_profiler.egg-info/top_level.txt
profiling/__init__.py
profiling/test/__init__.py