Metadata-Version: 1.1
Name: django-profiler
Version: 2.0.0
Summary: util for profiling python code mainly in django projects, but can be used also on ordinary python code
Home-page: http://www.codescale.net/en/community#django-profiler
Author: Vladimír Gorej
Author-email: gorej@codescale.net
License: BSD
Download-URL: http://github.com/char0n/django-profiler/tarball/master
Keywords: django profiler profiling code profile
Platform: any
Classifier: Development Status :: 5 - Production/Stable
Classifier: Environment :: Console
Classifier: Environment :: Web Environment
Classifier: Intended Audience :: Developers
Classifier: Intended Audience :: System Administrators
Classifier: License :: OSI Approved :: BSD License
Classifier: Operating System :: OS Independent
Classifier: Programming Language :: Python
Classifier: Topic :: Utilities
Classifier: Topic :: Software Development :: Debuggers
Classifier: Topic :: Software Development :: Bug Tracking
